ffpyplayer/pic.pyi
ffpyplayer/writer.pyi
ffpyplayer/player/__init__.pyi
ffpyplayer/player/player.pyi
ffpyplayer_stubs-1.0.0.dist-info/licenses/LICENSE
ffpyplayer_stubs-1.0.0.dist-info/METADATA
ffpyplayer_stubs-1.0.0.dist-info/WHEEL
ffpyplayer_stubs-1.0.0.dist-info/top_level.txt
ffpyplayer_stubs-1.0.0.dist-info/RECORD
