Metadata-Version: 2.4
Name: ffpyplayer-stubs
Version: 1.0.0
Summary: Type stubs for ffpyplayer
Author-email: wry <wry_by01@outlook.com>
License: The MIT License (MIT)
Project-URL: Homepage, https://github.com/yourusername/mypackage-stubs
Classifier: License :: OSI Approved :: MIT License
Classifier: Programming Language :: Python :: 3
Classifier: Typing :: Stubs Only
Requires-Python: >=3.8
License-File: LICENSE
Dynamic: license-file
